v2ex/__init__.py
v2ex/v2ex.py
v2ex_py-1.0.4.dist-info/LICENSE
v2ex_py-1.0.4.dist-info/METADATA
v2ex_py-1.0.4.dist-info/WHEEL
v2ex_py-1.0.4.dist-info/top_level.txt
v2ex_py-1.0.4.dist-info/RECORD
