Metadata-Version: 2.1
Name: v2ex-py
Version: 1.0.4
Summary: 一个标准调用V2EX RESTful API2.0的 Python API SDK
Author-email: Zerek <Zerek00@163.com>
License: GNU GENERAL PUBLIC LICENSE
Project-URL: Homepage, https://github.com/Zerek-Cheng/V2EX_for_pypi
Project-URL: Bug Tracker, https://github.com/Zerek-Cheng/V2EX_for_pypi/issues
Classifier: Programming Language :: Python :: 3
Classifier: License :: OSI Approved :: MIT License
Classifier: Operating System :: OS Independent
Requires-Python: >=3.8
License-File: LICENSE
